changelog/__init__.py
changelog/apps.py
changelog/decorators.py
changelog/managers.py
changelog/utils.py
changelog/admin/__init__.py
changelog/admin/commit.py
changelog/admin/release.py
changelog/admin/repository.py
changelog/admin/telegram.py
changelog/management/__init__.py
changelog/management/commands/__init__.py
changelog/management/commands/refresh_changelog.py
changelog/migrations/0001_initial.py
changelog/migrations/0002_delete_all_previous.py
changelog/migrations/0003_initial.py
changelog/migrations/__init__.py
changelog/models/__init__.py
changelog/models/commit.py
changelog/models/release.py
changelog/models/repository.py
changelog/models/telegram.py
changelog/templates/admin/commit_change_form.html
changelog/templates/admin/release_change_form.html
changelog/templates/admin/repository_change_form.html
changelog/templates/changelog/base.html
changelog/templates/changelog/email.html
changelog/templates/changelog/telegram.html
changelog/templates/changelog/telegram_first.html
django_git_changelog-0.5.4.dist-info/METADATA
django_git_changelog-0.5.4.dist-info/WHEEL
django_git_changelog-0.5.4.dist-info/top_level.txt
django_git_changelog-0.5.4.dist-info/RECORD
