Metadata-Version: 2.1
Name: django-git-changelog
Version: 0.5.4
Summary: List all git commits in the backend and create E-Mails with change informations
Home-page: UNKNOWN
Author: Snake-Soft
Author-email: info@snake-soft.com
License: GPL3
Platform: UNKNOWN
Classifier: Development Status :: 4 - Beta
Classifier: Environment :: Web Environment
Classifier: Framework :: Django
Classifier: Framework :: Django :: 3.2
Classifier: Intended Audience :: Developers
Classifier: License :: OSI Approved :: BSD License
Classifier: Operating System :: Unix
Classifier: Programming Language :: Python
Classifier: Programming Language :: Python :: 3
Classifier: Programming Language :: Python :: 3.7
Classifier: Programming Language :: Python :: 3.8
Classifier: Programming Language :: Python :: 3.9
Requires-Dist: django (<3.3,>=3.2)
Provides-Extra: test
